{
  "package_name": "inventory-v1.3.2",
  "version": "1.3.2",
  "created": "2025-09-05T06:00:54Z",
  "package_size": 170782,
  "package_hash": "50efac35729f74e5ed8809a586b84b2209c472c08e8b4979153836ff2e448d02",
  "rollback_safe": true,
  "restarts_expected": 2,
  "dependencies": {
    "python_packages": [
      "reportlab==4.0.4",
      "qrcode[pil]==7.4.2"
    ]
  },
  "files_included": [
    "src/routes/",
    "src/templates/",
    "src/services/",
    "src/utils/",
    "src/main.py",
    "src/config.py",
    "src/database.py",
    "src/models.py"
  ],
  "upgrade_steps": [
    {
      "step": "backup",
      "description": "Backup current source code"
    },
    {
      "step": "extract", 
      "description": "Extract new package"
    },
    {
      "step": "install_deps",
      "description": "Install new Python dependencies"
    },
    {
      "step": "restart_service",
      "description": "Restart inventory-app service"
    },
    {
      "step": "validate",
      "description": "Run health checks"
    },
    {
      "step": "cleanup",
      "description": "Remove backup if successful"
    }
  ]
}
